owl/__init__.py
owl/__main__.py
owl/data_types/__init__.py
owl/data_types/owl_function.py
owl/environment.py
owl/error_message.py
owl/expr_visitor.py
owl/interpreter.py
owl/native_functions.py
owl/owl_ast/__init__.py
owl/owl_ast/expr.py
owl/owl_ast/stmt.py
owl/owl_error.py
owl/owl_token.py
owl/parser.py
owl/resolver/__init__.py
owl/resolver/expr_resolver.py
owl/resolver/resolver.py
owl/resolver/stmt_resolver.py
owl/scanner.py
owl/stmt_visitor.py
owl/token_type.py
owl/tool/__init__.py
owl/tool/ast_expr.template
owl/tool/ast_stmt.template
owl/tool/generate_ast.py
owl_lang-0.6.3.dist-info/entry_points.txt
owl_lang-0.6.3.dist-info/WHEEL
owl_lang-0.6.3.dist-info/METADATA
owl_lang-0.6.3.dist-info/RECORD
