Metadata-Version: 2.1
Name: owl-lang
Version: 0.6.3
Summary: The owl 🦉 programming language
License: MIT
Author: Hieu Tran
Author-email: hieutran106@gmail.com
Requires-Python: >=3.8,<4.0
Classifier: License :: OSI Approved :: MIT License
Classifier: Programming Language :: Python :: 3
Classifier: Programming Language :: Python :: 3.10
Classifier: Programming Language :: Python :: 3.8
Classifier: Programming Language :: Python :: 3.9
